googlex/__init__.py
googlex/user_agents.py
googlex-1.0.dist-info/LICENSE
googlex-1.0.dist-info/METADATA
googlex-1.0.dist-info/WHEEL
googlex-1.0.dist-info/top_level.txt
googlex-1.0.dist-info/RECORD
