Metadata-Version: 2.1
Name: googlex
Version: 1.0
Summary: This is a powerful library for building self robots in Rubika
Home-page: https://github.com/mrsalari/googlex
Author: mohammad saeed salari
Author-email: salari601601@gmail.com
Keywords: googlex,google,search,gogle,pyrubika,search google,google search
Classifier: Programming Language :: Python :: 3.6
Classifier: Programming Language :: Python :: 3.7
Classifier: Programming Language :: Python :: 3.8
Classifier: Programming Language :: Python :: 3.9
Classifier: Programming Language :: Python :: 3.10
Classifier: Programming Language :: Python :: 3.11
Classifier: License :: OSI Approved :: MIT License
Requires-Python: ~=3.7
License-File: LICENSE
Requires-Dist: pycryptodome
Requires-Dist: websocket-client
Requires-Dist: websockets
Requires-Dist: requests
Requires-Dist: aiohttp
Requires-Dist: pillow
Requires-Dist: mutagen
Requires-Dist: tinytag
